SecuMas/__init__.py
SecuMas/cusip.py
SecuMas/isin.py
SecuMas/main.py
SecuMas/sedol.py
rules/isin.py
src/__init__.py
src/main.py
SecuMas-0.0.1.4.dist-info/LICENSE
SecuMas-0.0.1.4.dist-info/METADATA
SecuMas-0.0.1.4.dist-info/WHEEL
SecuMas-0.0.1.4.dist-info/top_level.txt
SecuMas-0.0.1.4.dist-info/RECORD
