Metadata-Version: 2.1
Name: SecuMas
Version: 0.0.1.4
Summary: An application build for Securities Master platform
Home-page: https://secumas.dev
Author: A Deolekar
Author-email: sher.buk@gmail.com
License: MIT License
Project-URL: Documentation, https://secumas.dev/
Project-URL: Source, https://github.com/deolekar/SecuMas
Platform: any
Classifier: License :: OSI Approved :: MIT License
Classifier: Operating System :: OS Independent
Classifier: Programming Language :: Python
Classifier: Programming Language :: Python :: 3
Classifier: Programming Language :: Python :: 3.4
Classifier: Programming Language :: Python :: 3.5
Classifier: Programming Language :: Python :: 3.6
Classifier: Programming Language :: Python :: 3.7
Classifier: Programming Language :: Python :: 3.8
Classifier: Programming Language :: Python :: 3.9
Classifier: Programming Language :: Python :: 3.10
Classifier: Programming Language :: Python :: 3.11
Classifier: Programming Language :: Python :: 3.12
Classifier: Development Status :: 2 - Pre-Alpha
